pyyaml_util/__init__.py
pyyaml_util/yaml_util.py
pyyaml_util-1.0.0.dist-info/LICENSE
pyyaml_util-1.0.0.dist-info/METADATA
pyyaml_util-1.0.0.dist-info/WHEEL
pyyaml_util-1.0.0.dist-info/top_level.txt
pyyaml_util-1.0.0.dist-info/zip-safe
pyyaml_util-1.0.0.dist-info/RECORD
