Metadata-Version: 2.1
Name: pyyaml_util
Version: 1.0.0
Summary: yaml助手
Home-page: https://github.com/buyfakett
Author: buyfakett
Author-email: buyfakett@vip.qq.com
License: MIT
Requires-Python: >=3.6
License-File: LICENSE
Requires-Dist: pyyaml
